MANIFEST.in
README
setup.cfg
setup.py
gossamer/__init__.py
gossamer/cli.py
gossamer/constant.py
gossamer/data.py
gossamer/exc.py
gossamer/getGossamerEvents.js
gossamer/image.py
gossamer/input.js
gossamer/integration.py
gossamer/js.py
gossamer/main.py
gossamer/pageChangingObserver.js
gossamer/run.py
gossamer/step.py
gossamer/util.py