Metadata-Version: 1.1
Name: gossamerui
Version: 0.9.4
Summary: Website user interface regression testing
Home-page: https://github.com/ijl/gossamer
Author: Jack Lutz
Author-email: uijllji@gmail.com
License: Apache 2.0
Download-URL: https://github.com/ijl/gossamer/archive/0.9.4.tar.gz
Keywords: selenium webdriver testing regression ui automated visual diff screenshot huxley
Platform: UNKNOWN
Classifier: Development Status :: 4 - Beta
Classifier: Environment :: Console
Classifier: Intended Audience :: Developers
Classifier: Operating System :: OS Independent
Classifier: License :: OSI Approved :: Apache Software License
Classifier: Programming Language :: Python
Classifier: Programming Language :: Python :: 2
Classifier: Topic :: Software Development :: Testing
Classifier: Topic :: Software Development :: Quality Assurance
Classifier: Topic :: Software Development :: Libraries :: Python Modules
